discordme/__init__.py
discordme/discord_api.py
discordme/utils.py
discordme.py-0.1.0.dist-info/METADATA
discordme.py-0.1.0.dist-info/WHEEL
discordme.py-0.1.0.dist-info/top_level.txt
discordme.py-0.1.0.dist-info/RECORD
