Metadata-Version: 2.2
Name: discordme.py
Version: 0.1.0
Summary: Une bibliothèque Python open-source permetant d'interagir simplement avec Discord
Home-page: https://github.com/wathdb/discordme.py
Author: wathD
Author-email: wathd_developement@proton.me
Classifier: Programming Language :: Python :: 3
Classifier: License :: OSI Approved :: MIT License
Classifier: Operating System :: OS Independent
Requires-Python: >=3.6
Dynamic: author
Dynamic: author-email
Dynamic: classifier
Dynamic: description-content-type
Dynamic: home-page
Dynamic: requires-python
Dynamic: summary
